[{"regionId":"16","regionType":"State","regionName":"Луганська область","regionEngName":"Luhanska region","lastUpdate":"2022-04-04T16:45:00Z","activeAlerts":[{"regionId":"16","regionType":"State","type":"AIR","lastUpdate":"2022-04-04T16:45:00Z"}]},{"regionId":"9999","regionType":"State","regionName":"Автономна Республіка Крим","regionEngName":"","lastUpdate":"2022-12-10T22:22:00Z","activeAlerts":[{"regionId":"9999","regionType":"State","type":"AIR","lastUpdate":"2022-12-10T22:22:00Z"}]},{"regionId":"28","regionType":"State","regionName":"Донецька область","regionEngName":"Donetska region","lastUpdate":"2024-04-07T18:24:28Z","activeAlerts":[{"regionId":"28","regionType":"State","type":"AIR","lastUpdate":"2024-04-07T18:24:17Z"}]},{"regionId":"351","regionType":"Community","regionName":"м. Нікополь та Нікопольська територіальна громада","regionEngName":"Nikopol and Nikopolska community","lastUpdate":"2024-04-07T18:55:58Z","activeAlerts":[{"regionId":"351","regionType":"Community","type":"ARTILLERY","lastUpdate":"2024-04-07T18:55:58Z"}]},{"regionId":"22","regionType":"State","regionName":"Харківська область","regionEngName":"Kharkivska region","lastUpdate":"2024-04-07T18:57:34Z","activeAlerts":[{"regionId":"22","regionType":"State","type":"AIR","lastUpdate":"2024-04-07T18:57:27Z"}]},{"regionId":"356","regionType":"Community","regionName":"Червоногригорівська територіальна громада","regionEngName":"Chervonohryhorivska community","lastUpdate":"2024-04-07T19:20:09Z","activeAlerts":[{"regionId":"356","regionType":"Community","type":"ARTILLERY","lastUpdate":"2024-04-07T19:20:09Z"}]}]